poetry_creator/__init__.py
poetry_creator/create_poetry.py
poetry_creator-0.1.1.dist-info/METADATA
poetry_creator-0.1.1.dist-info/WHEEL
poetry_creator-0.1.1.dist-info/entry_points.txt
poetry_creator-0.1.1.dist-info/top_level.txt
poetry_creator-0.1.1.dist-info/RECORD
