Metadata-Version: 2.1
Name: poetry-creator
Version: 0.1.1
Summary: The quickest way to get up and running with Python
Home-page: https://github.com/grp06/poetry-creator
Author: George Pickett
Author-email: gpickett00@gmail.com
Classifier: Development Status :: 3 - Alpha
Classifier: Intended Audience :: Developers
Classifier: License :: OSI Approved :: MIT License
Classifier: Programming Language :: Python :: 3.11
Requires-Dist: poetry
